sentry_chalice/__init__.py
sentry_chalice/sentry_chalice.py
sentry_chalice/version.py
tests/__init__.py
tests/conftest.py
tests/test_sentry_chalice.py
sentry_chalice-0.3.3.dist-info/LICENSE
sentry_chalice-0.3.3.dist-info/METADATA
sentry_chalice-0.3.3.dist-info/WHEEL
sentry_chalice-0.3.3.dist-info/top_level.txt
sentry_chalice-0.3.3.dist-info/RECORD
