Metadata-Version: 2.1
Name: sentry-chalice
Version: 0.3.3
Summary: exceptions on chalice
Home-page: https://github.com/cuenca-mx/sentry-chalice
Author: Cuenca
Author-email: dev@cuenca.com
License: UNKNOWN
Platform: UNKNOWN
Classifier: Programming Language :: Python :: 3
Classifier: Programming Language :: Python :: 3.6
Classifier: Programming Language :: Python :: 3.7
Classifier: Programming Language :: Python :: 3.8
Classifier: License :: OSI Approved :: MIT License
Classifier: Operating System :: OS Independent
Requires-Python: >=3.6
Requires-Dist: chalice (<1.20.0,>=1.16.0)
Requires-Dist: sentry-sdk (<0.18.0,>=0.16.2)
Requires-Dist: dataclasses (>=0.6) ; python_version < "3.7"
